BeginnersbookJspJiaochengChuyi/README.md
BeginnersbookJspJiaochengChuyi/__init__.py
BeginnersbookJspJiaochengChuyi/__main__.py
BeginnersbookJspJiaochengChuyi/file.epub
BeginnersbookJspJiaochengChuyi/index.html
BeginnersbookJspJiaochengChuyi/css/__init__.py
BeginnersbookJspJiaochengChuyi/css/annotations.css
BeginnersbookJspJiaochengChuyi/css/main.css
BeginnersbookJspJiaochengChuyi/css/normalize.css
BeginnersbookJspJiaochengChuyi/css/popup.css
BeginnersbookJspJiaochengChuyi/font/__init__.py
BeginnersbookJspJiaochengChuyi/font/fontello.eot
BeginnersbookJspJiaochengChuyi/font/fontello.svg
BeginnersbookJspJiaochengChuyi/font/fontello.ttf
BeginnersbookJspJiaochengChuyi/font/fontello.woff
BeginnersbookJspJiaochengChuyi/img/__init__.py
BeginnersbookJspJiaochengChuyi/img/annotator-glyph-sprite.png
BeginnersbookJspJiaochengChuyi/img/annotator-icon-sprite.png
BeginnersbookJspJiaochengChuyi/img/apple-touch-icon.png
BeginnersbookJspJiaochengChuyi/img/cancelfullscreen.png
BeginnersbookJspJiaochengChuyi/img/close.png
BeginnersbookJspJiaochengChuyi/img/fullscreen.png
BeginnersbookJspJiaochengChuyi/img/loader.gif
BeginnersbookJspJiaochengChuyi/img/menu-icon.png
BeginnersbookJspJiaochengChuyi/img/save.png
BeginnersbookJspJiaochengChuyi/img/saved.png
BeginnersbookJspJiaochengChuyi/img/settings-s.png
BeginnersbookJspJiaochengChuyi/img/settings.png
BeginnersbookJspJiaochengChuyi/img/star.png
BeginnersbookJspJiaochengChuyi/js/__init__.py
BeginnersbookJspJiaochengChuyi/js/epub.js
BeginnersbookJspJiaochengChuyi/js/epub.min.js
BeginnersbookJspJiaochengChuyi/js/epub.min.map
BeginnersbookJspJiaochengChuyi/js/hooks.min.js
BeginnersbookJspJiaochengChuyi/js/hooks.min.map
BeginnersbookJspJiaochengChuyi/js/reader.js
BeginnersbookJspJiaochengChuyi/js/reader.js.map
BeginnersbookJspJiaochengChuyi/js/reader.min.js
BeginnersbookJspJiaochengChuyi/js/reader.min.map
BeginnersbookJspJiaochengChuyi/js/hooks/__init__.py
BeginnersbookJspJiaochengChuyi/js/hooks/extensions/__init__.py
beginnersbook_jsp_jiaocheng_chuyi-2024.3.5.0.dist-info/METADATA
beginnersbook_jsp_jiaocheng_chuyi-2024.3.5.0.dist-info/WHEEL
beginnersbook_jsp_jiaocheng_chuyi-2024.3.5.0.dist-info/entry_points.txt
beginnersbook_jsp_jiaocheng_chuyi-2024.3.5.0.dist-info/top_level.txt
beginnersbook_jsp_jiaocheng_chuyi-2024.3.5.0.dist-info/RECORD
